talk_codebase/__init__.py
talk_codebase/cli.py
talk_codebase/config.py
talk_codebase/consts.py
talk_codebase/llm.py
talk_codebase/utils.py
talk_codebase-0.1.50.dist-info/LICENSE
talk_codebase-0.1.50.dist-info/METADATA
talk_codebase-0.1.50.dist-info/WHEEL
talk_codebase-0.1.50.dist-info/entry_points.txt
talk_codebase-0.1.50.dist-info/RECORD
