Metadata-Version: 2.1
Name: talk-codebase
Version: 0.1.50
Summary: talk-codebase is a powerful tool for querying and analyzing codebases.
Keywords: chatgpt,openai,cli
Author: Saryev Rustam
Author-email: rustam1997@gmail.com
Requires-Python: >=3.8.1,<4.0
Classifier: Programming Language :: Python :: 3
Classifier: Programming Language :: Python :: 3.9
Classifier: Programming Language :: Python :: 3.10
Classifier: Programming Language :: Python :: 3.11
Classifier: Programming Language :: Python :: 3.12
Requires-Dist: faiss-cpu (>=1.7.4,<2.0.0)
Requires-Dist: fire (>=0.5.0,<0.6.0)
Requires-Dist: gitpython (>=3.1.31,<4.0.0)
Requires-Dist: gpt4all (>=1.0.1,<2.0.0)
Requires-Dist: halo (>=0.0.31,<0.0.32)
Requires-Dist: langchain (>=0.0.223,<0.0.326)
Requires-Dist: llama-cpp-python (==0.1.68)
Requires-Dist: openai (>=0.27.7,<0.28.0)
Requires-Dist: questionary (>=1.10.0,<2.0.0)
Requires-Dist: sentence-transformers (>=2.2.2,<3.0.0)
Requires-Dist: tiktoken (>=0.4.0,<0.5.0)
Requires-Dist: unstructured (>=0.6.10,<0.7.0)
Requires-Dist: urllib3 (==1.26.18)
